dictionary/__init__.py
dictionary/dictionary.py
selin_cs453_hw1_section1-2.0.0.dist-info/METADATA
selin_cs453_hw1_section1-2.0.0.dist-info/WHEEL
selin_cs453_hw1_section1-2.0.0.dist-info/top_level.txt
selin_cs453_hw1_section1-2.0.0.dist-info/RECORD
